music_metadata_filter/__init__.py
music_metadata_filter/filter.py
music_metadata_filter/filters.py
music_metadata_filter/functions.py
music_metadata_filter/opinionated_filters.py
music_metadata_filter/opinionated_functions.py
music_metadata_filter/opinionated_rules.py
music_metadata_filter/rules.py
music_metadata_filter-3.0.0.data/data/share/doc/python-music-metadata-filter/LICENSE.md
music_metadata_filter-3.0.0.data/data/share/doc/python-music-metadata-filter/README.md
music_metadata_filter-3.0.0.dist-info/LICENSE.md
music_metadata_filter-3.0.0.dist-info/METADATA
music_metadata_filter-3.0.0.dist-info/WHEEL
music_metadata_filter-3.0.0.dist-info/top_level.txt
music_metadata_filter-3.0.0.dist-info/RECORD
