Metadata-Version: 2.1
Name: music-metadata-filter
Version: 3.0.0
Summary: A module for cleaning up artist, album, and song names.
Home-page: https://github.com/djmattyg007/music-metadata-filter
Author: Matthew Gamble
Author-email: git@matthewgamble.net
License: UNKNOWN
Platform: UNKNOWN
Classifier: Intended Audience :: Developers
Classifier: License :: OSI Approved :: MIT License
Classifier: Operating System :: OS Independent
Classifier: Programming Language :: Python :: 3
Classifier: Programming Language :: Python :: 3.8
Classifier: Programming Language :: Python :: 3.9
Classifier: Programming Language :: Python :: 3.10
Classifier: Topic :: Multimedia :: Sound/Audio :: Analysis
Requires-Python: >=3.8
License-File: LICENSE.md
